[
    {
        "id":1,
        "status":"New",
        "alertheading":"Battery Door Opened during surgery",
        "alertmessage":"Overheating,Poor Battery Life",
        "ticketid":"101230",
        "devicename":"",
        "dealername":"",
        "hospitalname":"Global Hospital",
        "stock": "",
        "alertdevice":"Services",
        "prioritystatus":"Very High",
        "orderstatus" : "Pending",
        "customerType": "Hospital",
        "customerId":"1",
        "serialNo": 1234512341,
        "partno":"XX05-001-000"
    
    },
    {
        "id":2,
        "status":"",
        "alertheading":"Battery Out of Life",
        "alertmessage":"Battery died,error message",
        "ticketid":"101256",
        "devicename":"Device Name",
        "dealername":"",
        "hospitalname":"",
        "stock":"",
        "alertdevice":"Devices",
        "prioritystatus":"High",
        "orderstatus" : "Pending",
        "customerType": "Dealer",
        "customerId":"3",
        "serialNo": 1234512342,
        "partno":"XX05-001-001"
    },
    {
        "id":3,
        "status":"",
        "alertheading":"Powertool stopped during surgery",
        "alertmessage":"Overheating,Poor Battery Life",
        "ticketid":"101258",
        "devicename":"",
        "dealername":"Dealer Name",
        "hospitalname":"",
        "stock":"",
        "alertdevice":"Services",
        "prioritystatus":"Very High",
        "orderstatus" : "Out of Stock",
        "customerType": "Dealer",
        "customerId":"4",
        "serialNo": 1234512343,
        "partno":"XX05-001-002"
    },
    {
        "id":4,
        "status":"",
        "alertheading":"Remb,Reciprocating Saw Out of Stock",
        "alertmessage":"P.No:XX05-001-000",
        "ticketid":"101478",
        "devicename":"",
        "dealername":"",
        "hospitalname":"",
        "stock":"0",
        "alertdevice":"Consumables",
        "prioritystatus":"High",
        "orderstatus" : "Pending",
        "customerType": "Hospital",
        "customerId":"2",
        "serialNo": 1234512344,
        "partno":"XX05-001-003"
    },
    {
        "id":5,
        "status":"",
        "alertheading":"Powertool working slow",
        "alertmessage":"Overheating,Poor Battery Life",
        "ticketid":"101456",
        "devicename":"",
        "dealername":"Dealer Name",
        "hospitalname":"",
        "stock":"",
        "alertdevice":"Services",
        "prioritystatus":"High",
        "orderstatus" : "Out of Stock",
        "customerType": "Service",
        "customerId":"5",
        "serialNo": 1234512345,
        "partno":"XX05-001-004"
    },
    {
        "id":6,
        "status":"",
        "alertheading":"Remb,Reciprocating slow",
        "alertmessage":"P.No:XX05-001-000",
        "ticketid":"101452",
        "devicename":"",
        "dealername":"",
        "hospitalname":"",
        "stock":"0",
        "alertdevice":"Services",
        "prioritystatus":"High",
        "orderstatus" : "Pending",
        "customerType": "Service",
        "customerId":"6",
        "serialNo": 1234512346,
        "partno":"XX05-001-005"
    }
]
