[
    {
      "item": "XX08001001",
      "discription": "Stryker Saggital Saw",
      "serial": "2230512345",
      "warrertytype": "Extended",
      "warrrentyexpiry": "29-07-2021"
    },
    {
      "item": "XX08001002",
      "discription": "Stryker module",
      "serial": "2230512378",
      "warrertytype": "Extended",
      "warrrentyexpiry": "21-05-2022"
    },
    {
      "item": "XX08001003",
      "discription": "Stryker Power",
      "serial": "2230512395",
      "warrertytype": "Extended",
      "warrrentyexpiry": "29-04-2023"
    },
    {
      "item": "XX08001004",
      "discription": "Stryker drill",
      "serial": "2230512378",
      "warrertytype": "Extended",
      "warrrentyexpiry": "29-07-2025"
    },
    {
      "item": "XX08001005",
      "discription": "Stryker charger",
      "serial": "2230512346",
      "warrertytype": "Extended",
      "warrrentyexpiry": "12-05-2026"
    },
    {
      "item": "XX08001006",
      "discription": "Stryker battery",
      "serial": "2230512457",
      "warrertytype": "Extended",
      "warrrentyexpiry": "13-06-2027"
    },
    {
      "item": "XX08001007",
      "discription": "Stryker drill",
      "serial": "2230590234",
      "warrertytype": "Regular",
      "warrrentyexpiry": "09-12-2022"
    },
    {
      "item": "XX08001008",
      "discription": "Stryker Saggital tool",
      "serial": "2230512458",
      "warrertytype": "Regular",
      "warrrentyexpiry": "21-06-2021"
    },
    {
      "item": "XX08001009",
      "discription": "Stryker Saggital bay",
      "serial": "2230512789",
      "warrertytype": "Extended",
      "warrrentyexpiry": "02-09-2022"
    },
    {
      "item": "XX08001010",
      "discription": "Stryker module",
      "serial": "223512345",
      "warrertytype": "Extended",
      "warrrentyexpiry": "18-01-2022"
    },
    {
      "item": "XX08001011",
      "discription": "Stryker battery",
      "serial": "223012345",
      "warrertytype": "Extended",
      "warrrentyexpiry": "21-04-2021"
    },
    {
      "item": "XX08001012",
      "discription": "Stryker power Saw",
      "serial": "223052345",
      "warrertytype": "Extended",
      "warrrentyexpiry": "29-07-2022"
    },
    {
      "item": "XX08001013",
      "discription": "Stryker batterty tool",
      "serial": "223051345",
      "warrertytype": "Extended",
      "warrrentyexpiry": "26-04-2022"
    },
    {
      "item": "XX08001014",
      "discription": "Stryker medium tool",
      "serial": "223052345",
      "warrertytype": "Extended",
      "warrrentyexpiry": "28-04-2022"
    },
    {
      "item": "XX08001015",
      "discription": "Stryker power module",
      "serial": "223051235",
      "warrertytype": "Extended",
      "warrrentyexpiry": "29-03-2022"
    },
    {
      "item": "XX08001016",
      "discription": "Stryker power Saw",
      "serial": "223052345",
      "warrertytype": "Extended",
      "warrrentyexpiry": "29-04-2022"
    },
    {
      "item": "XX08001017",
      "discription": "Stryker Battery",
      "serial": "223051245",
      "warrertytype": "Extended",
      "warrrentyexpiry": "29-04-2022"
    },
    {
      "item": "XX08001018",
      "discription": "StrykerDrill",
      "serial": "223051245",
      "warrertytype": "Extended",
      "warrrentyexpiry": "29-04-2022"
    }
  ]